invenio_sipstore/__init__.py
invenio_sipstore/admin.py
invenio_sipstore/api.py
invenio_sipstore/config.py
invenio_sipstore/errors.py
invenio_sipstore/ext.py
invenio_sipstore/models.py
invenio_sipstore/proxies.py
invenio_sipstore/signals.py
invenio_sipstore/utils.py
invenio_sipstore/version.py
invenio_sipstore/archivers/__init__.py
invenio_sipstore/archivers/bagit_archiver.py
invenio_sipstore/archivers/base_archiver.py
invenio_sipstore/archivers/utils.py
invenio_sipstore/jsonschemas/__init__.py
invenio_sipstore/jsonschemas/sipstore/agent-v1.0.0.json
invenio_sipstore/jsonschemas/sipstore/bagit-v1.0.0.json
invenio_sipstore/jsonschemas/sipstore/file-v1.0.0.json
invenio_sipstore/alembic/1c4e509ccacc_migrate_sip_content.py
invenio_sipstore/alembic/ac2d9845d16f_create_sipstore_branch.py
invenio_sipstore/alembic/ad6ee57b71f9_create_sipstore_tables.py
invenio_sipstore/alembic/b31cad2f14c7_extend_sip_metadata_model.py
invenio_sipstore-1.0.0a7.dist-info/top_level.txt
invenio_sipstore-1.0.0a7.dist-info/entry_points.txt
invenio_sipstore-1.0.0a7.dist-info/METADATA
invenio_sipstore-1.0.0a7.dist-info/DESCRIPTION.rst
invenio_sipstore-1.0.0a7.dist-info/metadata.json
invenio_sipstore-1.0.0a7.dist-info/WHEEL
invenio_sipstore-1.0.0a7.dist-info/RECORD
